seqseek/__init__.py
seqseek/chromosome.py
seqseek/cli.py
seqseek/downloader.py
seqseek/exceptions.py
seqseek/format_fasta.py
seqseek/lib.py
seqseek/tests/__init__.py
seqseek/tests/test_functional.py
seqseek/tests/test_meta_test.py
seqseek/tests/build_specific_tests/__init__.py
seqseek/tests/build_specific_tests/build_37_tests.py
seqseek/tests/build_specific_tests/build_38_tests.py
seqseek/tests/build_specific_tests/build_specific_tests.py
seqseek-0.4.2.dist-info/LICENSE
seqseek-0.4.2.dist-info/METADATA
seqseek-0.4.2.dist-info/WHEEL
seqseek-0.4.2.dist-info/entry_points.txt
seqseek-0.4.2.dist-info/top_level.txt
seqseek-0.4.2.dist-info/RECORD
